ansys/api/workbench/VERSION
ansys/api/workbench/__init__.py
ansys/api/workbench/py.typed
ansys/api/workbench/v0/workbench.proto
ansys/api/workbench/v0/workbench_pb2.py
ansys/api/workbench/v0/workbench_pb2.pyi
ansys/api/workbench/v0/workbench_pb2_grpc.py
ansys/api/workbench/v0/workbench_pb2_grpc.pyi
ansys_api_workbench-0.2.0.dist-info/AUTHORS
ansys_api_workbench-0.2.0.dist-info/LICENSE
ansys_api_workbench-0.2.0.dist-info/METADATA
ansys_api_workbench-0.2.0.dist-info/WHEEL
ansys_api_workbench-0.2.0.dist-info/entry_points.txt
ansys_api_workbench-0.2.0.dist-info/top_level.txt
ansys_api_workbench-0.2.0.dist-info/RECORD
