Metadata-Version: 2.1
Name: ansys-api-workbench
Version: 0.2.0
Summary: Autogenerated python gRPC interface package for ansys-api-workbench, built on 15:27:32 on 12 June 2024
Home-page: https://github.com/ansys-internal/ansys-api-workbench
Author: ANSYS, Inc.
Author-email: pyansys.core@ansys.com
License: MIT
Project-URL: Source, https://github.com/ansys/ansys-api-workbench/
Project-URL: Tracker, https://github.com/ansys/ansys-api-workbench/issues/
Project-URL: Documentation, https://github.com/ansys/ansys-api-workbench/#readme
Requires-Python: >=3.7
License-File: LICENSE
License-File: AUTHORS
Requires-Dist: grpcio ~=1.47
Requires-Dist: protobuf <6,>=3.19
